dialogflow_fulfillment/__init__.py
dialogflow_fulfillment/contexts.py
dialogflow_fulfillment/webhook_client.py
dialogflow_fulfillment/rich_responses/__init__.py
dialogflow_fulfillment/rich_responses/base.py
dialogflow_fulfillment/rich_responses/card.py
dialogflow_fulfillment/rich_responses/image.py
dialogflow_fulfillment/rich_responses/payload.py
dialogflow_fulfillment/rich_responses/quick_replies.py
dialogflow_fulfillment/rich_responses/text.py
dialogflow_fulfillment-0.4.4.dist-info/LICENSE
dialogflow_fulfillment-0.4.4.dist-info/METADATA
dialogflow_fulfillment-0.4.4.dist-info/WHEEL
dialogflow_fulfillment-0.4.4.dist-info/top_level.txt
dialogflow_fulfillment-0.4.4.dist-info/RECORD
