Metadata-Version: 2.1
Name: dialogflow-fulfillment
Version: 0.4.4
Summary: Create webhook services for Dialogflow using Python
Home-page: https://github.com/gcaccaos/dialogflow-fulfillment
Author: Gabriel Farias Caccáos
Author-email: gabriel.caccaos@gmail.com
License: Apache License 2.0
Project-URL: Documentation, https://dialogflow-fulfillment.readthedocs.io
Keywords: dialogflow,fulfillment,webhook,api,python
Platform: UNKNOWN
Classifier: Programming Language :: Python :: 3
Classifier: Programming Language :: Python :: 3 :: Only
Classifier: Programming Language :: Python :: 3.6
Classifier: Programming Language :: Python :: 3.7
Classifier: Programming Language :: Python :: 3.8
Classifier: Intended Audience :: Developers
Classifier: License :: OSI Approved :: Apache Software License
Classifier: Operating System :: OS Independent
Classifier: Topic :: Software Development :: Libraries :: Python Modules
Requires-Python: >=3
License-File: LICENSE
Provides-Extra: dev
Requires-Dist: tox (==3.24.1) ; extra == 'dev'
Requires-Dist: setuptools (==57.4.0) ; extra == 'dev'
Requires-Dist: wheel (==0.36.2) ; extra == 'dev'
Requires-Dist: twine (==3.4.2) ; extra == 'dev'
Provides-Extra: docs
Requires-Dist: sphinx (==4.1.2) ; extra == 'docs'
Requires-Dist: sphinx-autobuild (==2021.3.14) ; extra == 'docs'
Requires-Dist: sphinx-rtd-theme (==0.5.2) ; extra == 'docs'
Requires-Dist: sphinxcontrib-mermaid (==0.7.1) ; extra == 'docs'
Provides-Extra: lint
Requires-Dist: flake8 (==3.9.2) ; extra == 'lint'
Requires-Dist: flake8-docstrings (==1.6.0) ; extra == 'lint'
Requires-Dist: flake8-isort (==4.0.0) ; extra == 'lint'
Requires-Dist: pre-commit (==2.13.0) ; extra == 'lint'
Provides-Extra: tests
Requires-Dist: pytest (==6.2.4) ; extra == 'tests'
Requires-Dist: coverage (==5.5) ; extra == 'tests'
